curia/__init__.py
curia/api/.gitignore
curia/api/.swagger-codegen/VERSION
curia/api/.swagger-codegen-ignore
curia/api/.travis.yml
curia/api/README.md
curia/api/__init__.py
curia/api/docs/AggregationType.md
curia/api/docs/AllOfCohortModel.md
curia/api/docs/AllOfCohortOrganization.md
curia/api/docs/AllOfCohortTrainCohort.md
curia/api/docs/AllOfDataTableDataset.md
curia/api/docs/AllOfModelCohorts.md
curia/api/docs/AllOfModelJobDataset.md
curia/api/docs/AllOfModelJobEnvironment.md
curia/api/docs/AllOfModelJobModel.md
curia/api/docs/AllOfModelJobProject.md
curia/api/docs/AllOfModelModelJobs.md
curia/api/docs/AllOfModelProject.md
curia/api/docs/AnalysesApi.md
curia/api/docs/Analysis.md
curia/api/docs/AnalysisJob.md
curia/api/docs/AnalysisJobConfig.md
curia/api/docs/AnalysisJobJoinedProjectResponseDto.md
curia/api/docs/AnalysisJobOutput.md
curia/api/docs/AnalysisJobOutputJoinedAnalysisJobJoinedProjectResponseDto.md
curia/api/docs/AnalysisJobOutputJoinedAnalysisJobResponseDto.md
curia/api/docs/AnalysisJobOutputResponseDto.md
curia/api/docs/AnalysisJobOutputsApi.md
curia/api/docs/AnalysisJobResponseDto.md
curia/api/docs/AnalysisJobStatus.md
curia/api/docs/AnalysisJobStatusJoinedProjectResponseDto.md
curia/api/docs/AnalysisJobStatusResponseDto.md
curia/api/docs/AnalysisJobStatusesApi.md
curia/api/docs/AnalysisJobType.md
curia/api/docs/AnalysisJobsApi.md
curia/api/docs/AnalysisJoinedProjectResponseDto.md
curia/api/docs/AnalysisResponseDto.md
curia/api/docs/AnalysisType.md
curia/api/docs/AnyOfArithmeticExpressionValue.md
curia/api/docs/AnyOfBooleanExpressionValue.md
curia/api/docs/AnyOfCohortDefinitionPatientMetadataFiltersItems.md
curia/api/docs/AnyOfConditionValue.md
curia/api/docs/ArithmeticExpression.md
curia/api/docs/ArithmeticOperator.md
curia/api/docs/Body.md
curia/api/docs/Body1.md
curia/api/docs/Body2.md
curia/api/docs/Body3.md
curia/api/docs/Body4.md
curia/api/docs/Body5.md
curia/api/docs/BooleanExpression.md
curia/api/docs/Code.md
curia/api/docs/Cohort.md
curia-4.21.3.dist-info/METADATA
curia-4.21.3.dist-info/WHEEL
curia-4.21.3.dist-info/entry_points.txt
curia-4.21.3.dist-info/RECORD
