Metadata-Version: 2.3
Name: curia
Version: 4.21.3
Summary: A library for interfacing with the Curia API.
Author: Aledade, Inc.
Requires-Python: >=3.10,<4.0
Classifier: Programming Language :: Python :: 3
Classifier: Programming Language :: Python :: 3.10
Classifier: Programming Language :: Python :: 3.11
Classifier: Programming Language :: Python :: 3.12
Classifier: Programming Language :: Python :: 3.13
Requires-Dist: boto3 (>=1.26.0,<2.0.0)
Requires-Dist: certifi (>=2024.8.30)
Requires-Dist: click (>=8.1.7,<9.0.0)
Requires-Dist: flask (>=2.3.2,<4.0.0)
Requires-Dist: flask-cors (>=5.0.0,<6.0.0)
Requires-Dist: gitpython (>=3.1.43,<4.0.0)
Requires-Dist: hyperopt (>=0.2.7,<0.3.0)
Requires-Dist: logzero (>=1.7.0,<2.0.0)
Requires-Dist: mlflow (>=2.19.0,<3.0.0)
Requires-Dist: moto[ecr] (>=4.2.3,<5.0.0)
Requires-Dist: multipart (>=0.2.4,<0.3.0)
Requires-Dist: numpy (>=1.24.3,<2.0.0)
Requires-Dist: pandas (>=2.2.3,<3.0.0)
Requires-Dist: pillow (>=11.0.0,<12.0.0)
Requires-Dist: pyarrow (>=14.0.1,<15.0.0)
Requires-Dist: pymaybe (>=0.1.6,<0.2.0)
Requires-Dist: python-dateutil (>=2.5.3)
Requires-Dist: python-dotenv (>=1.0.0,<2.0.0)
Requires-Dist: requests (>=2.32.0,<3.0.0)
Requires-Dist: six (>=1.10)
Requires-Dist: urllib3 (>=1.15.1)
Requires-Dist: waitress (>=3.0.1,<4.0.0)
Requires-Dist: werkzeug (>=3.0.3,<4.0.0)
